getpixelcolor/__init__.py
getpixelcolor/static/get-pixel-color
GetPixelColor-0.2.19.dist-info/LICENSE
GetPixelColor-0.2.19.dist-info/METADATA
GetPixelColor-0.2.19.dist-info/WHEEL
GetPixelColor-0.2.19.dist-info/top_level.txt
GetPixelColor-0.2.19.dist-info/RECORD
