Metadata-Version: 2.1
Name: GetPixelColor
Version: 0.2.19
Summary: A cross-platform python library for getting the color of a given pixel on screen.
Home-page: https://github.com/Bobrobot1/GetPixelColor
Author: Bobrobot1
Author-email: Bobrobot1 <bobrobot@zoho.com>
License: MIT
Project-URL: GitHub, https://github.com/Bobrobot1/GetPixelColor
Project-URL: Bug Tracker, https://github.com/Bobrobot1/GetPixelColor/issues
Platform: Windows
Platform: Linux
Platform: Mac OS X
Classifier: Development Status :: 5 - Production/Stable
Classifier: Intended Audience :: Developers
Classifier: License :: OSI Approved :: MIT License
Classifier: Operating System :: POSIX :: Linux
Classifier: Operating System :: MacOS :: MacOS X
Classifier: Operating System :: Microsoft :: Windows
Classifier: Programming Language :: Python :: 3
Requires-Python: >=3.8
License-File: LICENSE
Requires-Dist: Pillow
Requires-Dist: numpy
Requires-Dist: pyautogui
Requires-Dist: win32api ; platform_system == "Windows"
Requires-Dist: pyobjc ; platform_system == "darwin"
Requires-Dist: pyobjc-core ; platform_system == "darwin"
Requires-Dist: pasteboard ; platform_system == "darwin"
